LICENSE.txt
MANIFEST.in
README.md
requirements.txt
setup.cfg
setup.py
thriftybuilder/__init__.py
thriftybuilder/_logging.py
thriftybuilder/build_configurations.py
thriftybuilder/builders.py
thriftybuilder/checksums.py
thriftybuilder/cli.py
thriftybuilder/common.py
thriftybuilder/configuration.py
thriftybuilder/containers.py
thriftybuilder/hashers.py
thriftybuilder/meta.py
thriftybuilder/storage.py
thriftybuilder/uploader.py
thriftybuilder.egg-info/PKG-INFO
thriftybuilder.egg-info/SOURCES.txt
thriftybuilder.egg-info/dependency_links.txt
thriftybuilder.egg-info/entry_points.txt
thriftybuilder.egg-info/requires.txt
thriftybuilder.egg-info/top_level.txt
thriftybuilder.egg-info/zip-safe
thriftybuilder/_external/__init__.py
thriftybuilder/_external/verbosity_argument_parser.py
thriftybuilder/tests/__init__.py
thriftybuilder/tests/_common.py
thriftybuilder/tests/_examples.py
thriftybuilder/tests/test_build_configurations.py
thriftybuilder/tests/test_builders.py
thriftybuilder/tests/test_checksums.py
thriftybuilder/tests/test_cli.py
thriftybuilder/tests/test_configuration.py
thriftybuilder/tests/test_storage.py
thriftybuilder/tests/test_uploader.py