Metadata-Version: 1.0
Name: thriftybuilder
Version: 1.1.0
Summary: Builds Docker images, capturing information to reduce the frequency of future re-builds
Home-page: https://github.com/wtsi-hgi/thrifty-builder
Author: UNKNOWN
Author-email: UNKNOWN
License: MIT
Platform: UNKNOWN
